Workbook

Sheet Instrucciones
B2: QUDOX · COTIZACIONES INTERNACIONALES
B3: Plantilla de cotización · Honduras
B4: Llená solo las celdas amarillas. El resto ya trae lo que QUDOX necesita ver, y los totales se calculan solos.
B6: Cómo llenarla
B7: 01 | C7: Abrí la hoja «Tus datos» y completá el nombre de la productora, contacto, registro fiscal, fecha y el impuesto que aplicás.
B8: 02 | C8: En cada hoja de marca, pegá tu logo dentro del recuadro punteado de arriba a la derecha (Insertar > Imagen).
B9: 03 | C9: Escribí el precio unitario de cada formato y de las coberturas, en dólares y solo el número. Por ejemplo: 150.
B10: 04 | C10: El presentador, el personaje «Azulito» y los props ya traen el monto fijo que QUDOX define. No hace falta tocarlos.
B11: 05 | C11: Completá los costos adicionales: se cobran solo cuando se usan, pero necesitamos el precio de cada uno.
B12: 06 | C12: Revisá la hoja «Resumen» y mandanos el archivo en Excel o exportado a PDF.
B14: Leyenda
C15: Celda amarilla: la llenás vos. El texto que escribís sale en azul.
C16: Celda gris o blanca: ya está definida por QUDOX o se calcula sola. Está bloqueada para que no se mueva.
B18: Condiciones
B19: · | C19: Una cotización por marca. Cada hoja de marca es una cotización aparte.
B20: · | C20: Precio desglosado por servicio y por formato. No queremos un monto global.
B21: · | C21: Las coberturas son intercambiables por una sesión de microtrends al mismo precio.
B22: · | C22: El pago se realiza a 45 días calendario contra entrega de factura en físico. El servicio es mes a mes.
B23: · | C23: Los montos del presentador, el Azulito y los props los asume la productora, que liquida directamente al talento.
B25: Guía completa: https://qudox-cotizaciones.pages.dev/

Sheet Tus datos
B2: TUS DATOS
B3: Se llenan una sola vez y aparecen en todas las hojas
B5: Productora | D5: Nombre comercial
B6: Persona de contacto
B7: Cargo
B8: Correo
B9: WhatsApp | D9: Con código de país
B10: Ciudad
B11: RTN | D11: Registro fiscal de la productora
B12: Sitio web o portafolio | D12: Link a trabajos anteriores
B13: N.° de cotización | D13: Tu numeración interna
B14: Fecha | D14: dd/mm/aaaa
B15: Vigencia (días) | D15: Cuántos días respetás estos precios
B16: ISV que aplicás (%) | D16: Escribí 15 para 15 %. Dejalo vacío si tus precios ya lo incluyen.

Sheet UNO
B2: COTIZACIÓN · PLAN MENSUAL | E2: Tu logo aquí (Insertar > Imagen)
B3: Gasolineras UNO
B4: Honduras · Cliente: QUDOX · Moneda: dólares (USD)
B8: Productora | C8: =IF('Tus datos'!$C$5="","—",'Tus datos'!$C$5) -> —
B9: Contacto | C9: =IF('Tus datos'!$C$6="","—",'Tus datos'!$C$6) -> —
B10: Correo | C10: =IF('Tus datos'!$C$8="","—",'Tus datos'!$C$8) -> —
B11: WhatsApp | C11: =IF('Tus datos'!$C$9="","—",'Tus datos'!$C$9) -> —
B12: RTN | C12: =IF('Tus datos'!$C$11="","—",'Tus datos'!$C$11) -> —
B13: N.° de cotización | C13: =IF('Tus datos'!$C$13="","—",'Tus datos'!$C$13) -> —
B14: Fecha | C14: =IF('Tus datos'!$C$14="","—",'Tus datos'!$C$14) -> —
B15: Vigencia | C15: =IF('Tus datos'!$C$15="","—",'Tus datos'!$C$15&" días") -> —
B17: Concepto | C17: Qué incluye | D17: Cantidad | E17: Precio unitario | F17: Subtotal
B18: 1. Short videos · 7 videos al mes
B19: Producción | C19: Dificultad alta. Guion creativo, grabación, dirección y edición extensa: logos, animaciones, subtítulos de marca, transiciones y efectos de sonido. | D19: 3 | F19: =D19*E19 -> 0
B20: Microproducción | C20: Dificultad media. Idea general y CTA, grabación, dirección y edición general, orgánica y sin subtítulos. | D20: 2 | F20: =D20*E20 -> 0
B21: Tendencia | C21: Dificultad baja. Lectura de la tendencia, grabación, dirección y edición general con textos y gráficos en pantalla. | D21: 2 | F21: =D21*E21 -> 0
B22: Presentador | C22: L3,312 que se le pagan al talento por los 7 videos. Pago mensual fijo. | D22: 1 | E22: 125 | F22: =D22*E22 -> 125
B23: Personaje «Azulito» | C23: Aparece en cerca del 50 % de los videos. El disfraz lo provee el cliente; la productora se encarga del resguardo, lavado y planchado. | D23: 1 | E23: 35 | F23: =D23*E23 -> 35
B24: Props e impresiones | C24: Compra de materiales e impresión física de artes. Monto fijo mensual, aunque no se use todo. | D24: 1 | E24: 35 | F24: =D24*E24 -> 35
B25: Subtotal short videos | F25: =SUM(F19:F24) -> 195
B27: 2. Coberturas · 2 al mes
B28: Cobertura estándar de hasta 3 h | C28: Entregables: 8 historias en tiempo real, 25 a 30 fotos editadas y 1 video recap vertical de máx. 1 min. Herramientas: Cámara profesional solo para fotografías. Historias y video recap con celular, micrófonos, estabilizador y luces. Intercambiable por una sesión de microtrends (4 piezas en crudo) al mismo precio. | D28: 2 | F28: =D28*E28 -> 0
B29: Subtotal coberturas | F29: =SUM(F28:F28) -> 0
D31: Subtotal plan mensual | F31: =F25+F29 -> 195
D32: ="ISV ("&IF('Tus datos'!$C$16="",0,'Tus datos'!$C$16)&" %)" -> ISV (0 %) | F32: =IF('Tus datos'!$C$16="",0,F31*'Tus datos'!$C$16/100) -> 0
D33: Total plan mensual | F33: =F31+F32 -> 195
B35: Costos adicionales · fuera del plan, se cobran solo cuando se usan
B36: Jornada fuera del área metropolitana | C36: Un solo costo por jornada: traslado, viáticos y tiempo del equipo. | D36: por jornada
B37: Cobertura nocturna o de concierto | C37: De 4 a 5 h. Entregables: 8 historias, de 30 a 35 fotos editadas y 1 video recap. Mismas herramientas que la estándar. | D37: por cobertura
B38: Cobertura en formato pro | C38: Equipo de 3 personas (fotógrafo, videógrafo y creador de contenido). Cámara profesional también para video y recap, esquema de luces y, según el evento, dron o cámara 360. Mismos entregables que la cobertura que mejora. | D38: por cobertura
B40: Notas de la productora
B46: Pago a 45 días calendario contra entrega de factura en físico. Servicio mes a mes, sin contrato por plazo fijo.

Sheet PRONTO
B2: COTIZACIÓN · PLAN MENSUAL | E2: Tu logo aquí (Insertar > Imagen)
B3: Tiendas PRONTO
B4: Honduras · Cliente: QUDOX · Moneda: dólares (USD)
B8: Productora | C8: =IF('Tus datos'!$C$5="","—",'Tus datos'!$C$5) -> —
B9: Contacto | C9: =IF('Tus datos'!$C$6="","—",'Tus datos'!$C$6) -> —
B10: Correo | C10: =IF('Tus datos'!$C$8="","—",'Tus datos'!$C$8) -> —
B11: WhatsApp | C11: =IF('Tus datos'!$C$9="","—",'Tus datos'!$C$9) -> —
B12: RTN | C12: =IF('Tus datos'!$C$11="","—",'Tus datos'!$C$11) -> —
B13: N.° de cotización | C13: =IF('Tus datos'!$C$13="","—",'Tus datos'!$C$13) -> —
B14: Fecha | C14: =IF('Tus datos'!$C$14="","—",'Tus datos'!$C$14) -> —
B15: Vigencia | C15: =IF('Tus datos'!$C$15="","—",'Tus datos'!$C$15&" días") -> —
B17: Concepto | C17: Qué incluye | D17: Cantidad | E17: Precio unitario | F17: Subtotal
B18: 1. Short videos · 4 videos al mes
B19: Producción | C19: Dificultad alta. Guion creativo, grabación, dirección y edición extensa: logos, animaciones, subtítulos de marca, transiciones y efectos de sonido. | D19: 1 | F19: =D19*E19 -> 0
B20: Microproducción | C20: Dificultad media. Idea general y CTA, grabación, dirección y edición general, orgánica y sin subtítulos. | D20: 1 | F20: =D20*E20 -> 0
B21: Tendencia | C21: Dificultad baja. Lectura de la tendencia, grabación, dirección y edición general con textos y gráficos en pantalla. | D21: 2 | F21: =D21*E21 -> 0
B22: Presentador | C22: $80 que se le pagan al talento por los 4 videos. Pago mensual fijo. | D22: 1 | E22: 80 | F22: =D22*E22 -> 80
B23: Props e impresiones | C23: Compra de materiales e impresión física de artes. Monto fijo mensual, aunque no se use todo. | D23: 1 | E23: 35 | F23: =D23*E23 -> 35
B24: Subtotal short videos | F24: =SUM(F19:F23) -> 115
B26: 2. Coberturas · 1 al mes
B27: Cobertura estándar de hasta 3 h | C27: Entregables: 6 a 8 historias en tiempo real, 25 a 30 fotos editadas y 1 video recap vertical de máx. 1 min. Herramientas: Cámara profesional solo para fotografías. Historias y video recap con celular, micrófonos, estabilizador y luces. Intercambiable por una sesión de microtrends (6 piezas en crudo) al mismo precio. | D27: 1 | F27: =D27*E27 -> 0
B28: Subtotal coberturas | F28: =SUM(F27:F27) -> 0
D30: Subtotal plan mensual | F30: =F24+F28 -> 115
D31: ="ISV ("&IF('Tus datos'!$C$16="",0,'Tus datos'!$C$16)&" %)" -> ISV (0 %) | F31: =IF('Tus datos'!$C$16="",0,F30*'Tus datos'!$C$16/100) -> 0
D32: Total plan mensual | F32: =F30+F31 -> 115
B34: Costos adicionales · fuera del plan, se cobran solo cuando se usan
B35: Jornada fuera del área metropolitana | C35: Un solo costo por jornada: traslado, viáticos y tiempo del equipo. | D35: por jornada
B36: Cobertura en formato pro | C36: Equipo de 3 personas (fotógrafo, videógrafo y creador de contenido). Cámara profesional también para video y recap, esquema de luces y, según el evento, dron o cámara 360. Mismos entregables que la cobertura que mejora. | D36: por cobertura
B38: Notas de la productora
B44: Pago a 45 días calendario contra entrega de factura en físico. Servicio mes a mes, sin contrato por plazo fijo.

Sheet Resumen
B2: RESUMEN
B3: Totales por marca · Honduras
B4: Se calcula solo con lo que llenaste en cada hoja. Montos en USD.
B6: Cotización | C6: Short videos | D6: Coberturas | E6: Subtotal | F6: ISV | G6: Total mensual
B7: UNO | C7: =UNO!F25 -> 195 | D7: =UNO!F29 -> 0 | E7: =UNO!F31 -> 195 | F7: =UNO!F32 -> 0 | G7: =UNO!F33 -> 195
B8: PRONTO | C8: =PRONTO!F24 -> 115 | D8: =PRONTO!F28 -> 0 | E8: =PRONTO!F30 -> 115 | F8: =PRONTO!F31 -> 0 | G8: =PRONTO!F32 -> 115
